[
    {
        "alg": "SHA-256",
        "type": "DEPOSIT",
        "to_iban": "ES9121000418450200051332",
        "deposit_amount": 2500.0,
        "deposit_date": 1742942110.872133,
        "deposit_signature": "8b714730b74cfafe1b837f5633c7c4e3a7ac9376cd623300c328e01799af10d6"
    },
    {
        "alg": "SHA-256",
        "type": "DEPOSIT",
        "to_iban": "ES9121000418450200051332",
        "deposit_amount": 2500.0,
        "deposit_date": 1742942411.398783,
        "deposit_signature": "f633173c334c1e9e1efbcc0f0f511c8d74548d78f686306c38344649571492ec"
    },
    {
        "alg": "SHA-256",
        "type": "DEPOSIT",
        "to_iban": "ES9121000418450200051332",
        "deposit_amount": 2500.0,
        "deposit_date": 1742942544.439593,
        "deposit_signature": "330d829cb0ec7031565c4da8b6f88090c2137f068899c2899419315eb2fd8b50"
    },
    {
        "alg": "SHA-256",
        "type": "DEPOSIT",
        "to_iban": "ES9121000418450200051332",
        "deposit_amount": 2500.0,
        "deposit_date": 1742942554.733278,
        "deposit_signature": "4f9f8ffe4a58c1df7639ea5b543d4156749cf90fef59994757045a3e9a2f795d"
    },
    {
        "alg": "SHA-256",
        "type": "DEPOSIT",
        "to_iban": "ES9121000418450200051332",
        "deposit_amount": 2500.0,
        "deposit_date": 1742942565.10152,
        "deposit_signature": "012e63064e35a6d055870f90db567f658df3fa746118de54907f35b300496a69"
    },
    {
        "alg": "SHA-256",
        "type": "DEPOSIT",
        "to_iban": "ES9121000418450200051332",
        "deposit_amount": 2500.0,
        "deposit_date": 1742942574.933247,
        "deposit_signature": "659c4296614ed842ae3d0635b8ec968fa6091ed20f5426e373b3c22e33e44008"
    },
    {
        "alg": "SHA-256",
        "type": "DEPOSIT",
        "to_iban": "ES9121000418450200051332",
        "deposit_amount": 2500.0,
        "deposit_date": 1742942643.020161,
        "deposit_signature": "b62aa5316662b852cc838b5ff83b4d355bd4364042673442043083885b7543ad"
    },
    {
        "alg": "SHA-256",
        "type": "DEPOSIT",
        "to_iban": "ES9121000418450200051332",
        "deposit_amount": 2500.0,
        "deposit_date": 1742942657.499464,
        "deposit_signature": "d48649557c728aa87f9b30f41731a74ad59a66db72d80b913972e6eb6cf08274"
    },
    {
        "alg": "SHA-256",
        "type": "DEPOSIT",
        "to_iban": "ES9121000418450200051332",
        "deposit_amount": 2500.0,
        "deposit_date": 1742942694.366527,
        "deposit_signature": "b7e56f2787f9b1ba2cf60980db8928a92d4dc98ad4140e71315964ab8ae701c6"
    },
    {
        "alg": "SHA-256",
        "type": "DEPOSIT",
        "to_iban": "ES9121000418450200051332",
        "deposit_amount": 2500.0,
        "deposit_date": 1742942703.679253,
        "deposit_signature": "60b11d611b222e50f4d59d5bd83069f3d4f4f1077c46142a024b7a3ea8323eaf"
    },
    {
        "alg": "SHA-256",
        "type": "DEPOSIT",
        "to_iban": "ES9121000418450200051332",
        "deposit_amount": 2500.0,
        "deposit_date": 1742942901.355011,
        "deposit_signature": "78811b275ed907eafd380152183bc7d9c3950cf602629aa243700349b3c9a658"
    },
    {
        "alg": "SHA-256",
        "type": "DEPOSIT",
        "to_iban": "ES9121000418450200051332",
        "deposit_amount": 2500.0,
        "deposit_date": 1742943001.000276,
        "deposit_signature": "43a5b58e13dce745448523e3d4901f39170a8a3590a1a8106f67a8db18fc1661"
    },
    {
        "alg": "SHA-256",
        "type": "DEPOSIT",
        "to_iban": "ES9121000418450200051332",
        "deposit_amount": 2500.0,
        "deposit_date": 1742943062.936084,
        "deposit_signature": "c7bdcedcc1157693b80c5c131716561198266441ec21d5514344cee65c6f8ed9"
    },
    {
        "alg": "SHA-256",
        "type": "DEPOSIT",
        "to_iban": "ES9121000418450200051332",
        "deposit_amount": 2500.0,
        "deposit_date": 1742943226.894706,
        "deposit_signature": "1c06ecef7a55bc226b30c0b302482bfe7c6d22416daccccba1f095a5fce86155"
    },
    {
        "alg": "SHA-256",
        "type": "DEPOSIT",
        "to_iban": "ES9121000418450200051332",
        "deposit_amount": 2500.0,
        "deposit_date": 1742943263.035654,
        "deposit_signature": "514416bf9c2ed458b5d69f40741ab78d3d201fac4a9c4f2379e559541d3fead0"
    },
    {
        "alg": "SHA-256",
        "type": "DEPOSIT",
        "to_iban": "ES9121000418450200051332",
        "deposit_amount": 2500.0,
        "deposit_date": 1742943277.339645,
        "deposit_signature": "25594b9f713f2e01bf7c538aabbdb2ca64ccf1fd7612e37d98e299467a56aeb4"
    },
    {
        "alg": "SHA-256",
        "type": "DEPOSIT",
        "to_iban": "ES9121000418450200051332",
        "deposit_amount": 2500.0,
        "deposit_date": 1742943360.764616,
        "deposit_signature": "96783f9bf29d467b11924ad13206cf085f8caa0f18a8b15290234a967a000d6f"
    },
    {
        "alg": "SHA-256",
        "type": "DEPOSIT",
        "to_iban": "ES9121000418450200051332",
        "deposit_amount": 2500.0,
        "deposit_date": 1742943831.736997,
        "deposit_signature": "7f8e8a3918c3a1530ecc56645dcc20c0a00134d34559b8b4b2b9cab1f1ae106d"
    }
]